sitemapgenerator/__init__.py
sitemapgenerator/crawler.py
sitemapgenerator/sitemap.py
sitemapgenerator/sitemapgenerator.py
sitemapgenerator-0.1.0.dist-info/DESCRIPTION.rst
sitemapgenerator-0.1.0.dist-info/METADATA
sitemapgenerator-0.1.0.dist-info/RECORD
sitemapgenerator-0.1.0.dist-info/WHEEL
sitemapgenerator-0.1.0.dist-info/entry_points.txt
sitemapgenerator-0.1.0.dist-info/metadata.json
sitemapgenerator-0.1.0.dist-info/top_level.txt
