Metadata-Version: 2.0
Name: sitemapgenerator
Version: 0.1.0
Summary: Create an XML sitemap by crawling a website.
Home-page: https://github.com/techjacker/sitemapgenerator
Author: Andrew Griffiths
Author-email: mail@andrewgriffithsonline.com
License: MIT
Platform: UNKNOWN
Classifier: Development Status :: 5 - Production/Stable
Classifier: Natural Language :: English
Classifier: License :: OSI Approved :: MIT License
Classifier: Operating System :: OS Independent
Classifier: Programming Language :: Python
Classifier: Programming Language :: Python :: 3
Classifier: Programming Language :: Python :: 3.4
